dexa_sdk/__init__.py
dexa_sdk/agent/__init__.py
dexa_sdk/agent/admin/__init__.py
dexa_sdk/agent/admin/aiohttp_apispec/__init__.py
dexa_sdk/agent/admin/aiohttp_apispec/custom.py
dexa_sdk/agent/admin/aiohttp_apispec/static/favicon-16x16.ico
dexa_sdk/agent/admin/aiohttp_apispec/static/favicon-32x32.png
dexa_sdk/agent/admin/aiohttp_apispec/static/index.html
dexa_sdk/agent/admin/aiohttp_apispec/static/logo.svg
dexa_sdk/agent/admin/aiohttp_apispec/static/oauth2-redirect.html
dexa_sdk/agent/admin/aiohttp_apispec/static/swagger-ui-bundle.js
dexa_sdk/agent/admin/aiohttp_apispec/static/swagger-ui-bundle.js.map
dexa_sdk/agent/admin/aiohttp_apispec/static/swagger-ui-standalone-preset.js
dexa_sdk/agent/admin/aiohttp_apispec/static/swagger-ui-standalone-preset.js.map
dexa_sdk/agent/admin/aiohttp_apispec/static/swagger-ui.css
dexa_sdk/agent/admin/aiohttp_apispec/static/swagger-ui.css.map
dexa_sdk/agent/admin/aiohttp_apispec/static/swagger-ui.js
dexa_sdk/agent/admin/aiohttp_apispec/static/swagger-ui.js.map
dexa_sdk/agent/admin/aiohttp_apispec/static/theme-newspaper.css
dexa_sdk/agent/admin/server.py
dexa_sdk/agent/commands/__init__.py
dexa_sdk/agent/commands/start.py
dexa_sdk/agent/config/__init__.py
dexa_sdk/agent/config/argparse.py
dexa_sdk/agent/config/default_context.py
dexa_sdk/agent/config/dexa.py
dexa_sdk/agent/config/injection_context.py
dexa_sdk/agent/config/injector.py
dexa_sdk/agent/core/__init__.py
dexa_sdk/agent/core/conductor.py
dexa_sdk/agent/core/plugin_registry.py
dexa_sdk/agreements/__init__.py
dexa_sdk/agreements/da/__init__.py
dexa_sdk/agreements/da/v1_0/__init__.py
dexa_sdk/agreements/da/v1_0/models/__init__.py
dexa_sdk/agreements/da/v1_0/models/da_instance_models.py
dexa_sdk/agreements/da/v1_0/models/da_models.py
dexa_sdk/agreements/da/v1_0/models/tests/__init__.py
dexa_sdk/agreements/da/v1_0/models/tests/test_da_instance_models.py
dexa_sdk/agreements/da/v1_0/models/tests/test_da_models.py
dexa_sdk/agreements/da/v1_0/records/__init__.py
dexa_sdk-0.1.14.dist-info/LICENSE
dexa_sdk-0.1.14.dist-info/WHEEL
dexa_sdk-0.1.14.dist-info/METADATA
dexa_sdk-0.1.14.dist-info/RECORD
